efb_patch_middleware/__init__.py
efb_patch_middleware/__version__.py
efb_patch_middleware_itchat_uos-2.0.24.dist-info/LICENSE
efb_patch_middleware_itchat_uos-2.0.24.dist-info/METADATA
efb_patch_middleware_itchat_uos-2.0.24.dist-info/WHEEL
efb_patch_middleware_itchat_uos-2.0.24.dist-info/entry_points.txt
efb_patch_middleware_itchat_uos-2.0.24.dist-info/top_level.txt
efb_patch_middleware_itchat_uos-2.0.24.dist-info/RECORD
