Metadata-Version: 2.1
Name: efb-patch-middleware-itchat-uos
Version: 2.0.24
Summary: Patch middleware for EH Forwarder Bot, enhance functions.
Home-page: https://github.com/HoganGolden/efb-patch-middleware
Author: HoganKing
Author-email: 
License: AGPLv3+
Keywords: ehforwarderbot,EH Forwarder Bot,EH Forwarder Bot Middleware,Patch
Classifier: Development Status :: 3 - Alpha
Classifier: License :: OSI Approved :: GNU Affero General Public License v3 or later (AGPLv3+)
Classifier: Intended Audience :: Developers
Classifier: Intended Audience :: End Users/Desktop
Classifier: Programming Language :: Python :: 3 :: Only
Classifier: Programming Language :: Python :: 3.6
Classifier: Programming Language :: Python :: 3.7
Classifier: Topic :: Communications :: Chat
Classifier: Topic :: Utilities
Requires-Python: >=3.6
License-File: LICENSE
Requires-Dist: ehforwarderbot
Requires-Dist: efb-telegram-master
Requires-Dist: efb-wechat-slave-itchat-uos
Requires-Dist: python-telegram-bot
Requires-Dist: peewee
Requires-Dist: PyYaml
Requires-Dist: Pillow
